[
  {
    "ContainingType": "MvcCoreProject.Controllers.Api.AttendanceApiController",
    "Method": "ProcessAttendanceAction",
    "RelativePath": "api/attendance/action",
    "HttpMethod": "POST",
    "IsController": true,
    "Order": 0,
    "Parameters": [
      {
        "Name": "request",
        "Type": "CoreProject.Utilities.DTOs.AttendanceActionRequestDto",
        "IsRequired": true
      }
    ],
    "ReturnTypes": [
      {
        "Type": "CoreProject.Utilities.DTOs.AttendanceActionResponseDto",
        "MediaTypes": [
          "text/plain",
          "application/json",
          "text/json"
        ],
        "StatusCode": 200
      },
      {
        "Type": "Microsoft.AspNetCore.Mvc.ProblemDetails",
        "MediaTypes": [
          "text/plain",
          "application/json",
          "text/json"
        ],
        "StatusCode": 400
      },
      {
        "Type": "Microsoft.AspNetCore.Mvc.ProblemDetails",
        "MediaTypes": [
          "text/plain",
          "application/json",
          "text/json"
        ],
        "StatusCode": 401
      }
    ]
  },
  {
    "ContainingType": "MvcCoreProject.Controllers.Api.AttendanceApiController",
    "Method": "GetActionStatus",
    "RelativePath": "api/attendance/action-status",
    "HttpMethod": "GET",
    "IsController": true,
    "Order": 0,
    "Parameters": [],
    "ReturnTypes": [
      {
        "Type": "CoreProject.Utilities.DTOs.ActionStatusResponseDto",
        "MediaTypes": [
          "text/plain",
          "application/json",
          "text/json"
        ],
        "StatusCode": 200
      },
      {
        "Type": "Microsoft.AspNetCore.Mvc.ProblemDetails",
        "MediaTypes": [
          "text/plain",
          "application/json",
          "text/json"
        ],
        "StatusCode": 400
      },
      {
        "Type": "Microsoft.AspNetCore.Mvc.ProblemDetails",
        "MediaTypes": [
          "text/plain",
          "application/json",
          "text/json"
        ],
        "StatusCode": 401
      }
    ]
  },
  {
    "ContainingType": "MvcCoreProject.Controllers.Api.AttendanceApiController",
    "Method": "Passthrough",
    "RelativePath": "api/attendance/passthrough",
    "HttpMethod": "POST",
    "IsController": true,
    "Order": 0,
    "Parameters": [
      {
        "Name": "request",
        "Type": "CoreProject.Utilities.DTOs.PassthroughRequestDto",
        "IsRequired": true
      }
    ],
    "ReturnTypes": [
      {
        "Type": "CoreProject.Utilities.DTOs.PassthroughResponseDto",
        "MediaTypes": [
          "text/plain",
          "application/json",
          "text/json"
        ],
        "StatusCode": 200
      },
      {
        "Type": "Microsoft.AspNetCore.Mvc.ProblemDetails",
        "MediaTypes": [
          "text/plain",
          "application/json",
          "text/json"
        ],
        "StatusCode": 400
      },
      {
        "Type": "Microsoft.AspNetCore.Mvc.ProblemDetails",
        "MediaTypes": [
          "text/plain",
          "application/json",
          "text/json"
        ],
        "StatusCode": 401
      }
    ]
  },
  {
    "ContainingType": "MvcCoreProject.Controllers.Api.AttendanceApiController",
    "Method": "GetUserProfile",
    "RelativePath": "api/attendance/profile",
    "HttpMethod": "GET",
    "IsController": true,
    "Order": 0,
    "Parameters": [],
    "ReturnTypes": [
      {
        "Type": "CoreProject.Utilities.DTOs.UserProfileResponseDto",
        "MediaTypes": [
          "text/plain",
          "application/json",
          "text/json"
        ],
        "StatusCode": 200
      },
      {
        "Type": "Microsoft.AspNetCore.Mvc.ProblemDetails",
        "MediaTypes": [
          "text/plain",
          "application/json",
          "text/json"
        ],
        "StatusCode": 401
      }
    ]
  },
  {
    "ContainingType": "MvcCoreProject.Controllers.Api.AttendanceApiController",
    "Method": "GetAttendanceReport",
    "RelativePath": "api/attendance/report",
    "HttpMethod": "GET",
    "IsController": true,
    "Order": 0,
    "Parameters": [
      {
        "Name": "DateFrom",
        "Type": "System.Nullable\u00601[[System.DateTime, System.Private.CoreLib, Version=8.0.0.0, Culture=neutral, PublicKeyToken=7cec85d7bea7798e]]",
        "IsRequired": false
      },
      {
        "Name": "DateTo",
        "Type": "System.Nullable\u00601[[System.DateTime, System.Private.CoreLib, Version=8.0.0.0, Culture=neutral, PublicKeyToken=7cec85d7bea7798e]]",
        "IsRequired": false
      }
    ],
    "ReturnTypes": [
      {
        "Type": "CoreProject.Utilities.DTOs.AttendanceReportResponseDto",
        "MediaTypes": [
          "text/plain",
          "application/json",
          "text/json"
        ],
        "StatusCode": 200
      },
      {
        "Type": "Microsoft.AspNetCore.Mvc.ProblemDetails",
        "MediaTypes": [
          "text/plain",
          "application/json",
          "text/json"
        ],
        "StatusCode": 400
      },
      {
        "Type": "Microsoft.AspNetCore.Mvc.ProblemDetails",
        "MediaTypes": [
          "text/plain",
          "application/json",
          "text/json"
        ],
        "StatusCode": 401
      }
    ]
  },
  {
    "ContainingType": "MvcCoreProject.Controllers.Api.AttendanceApiController",
    "Method": "CheckUserStatus",
    "RelativePath": "api/attendance/status",
    "HttpMethod": "GET",
    "IsController": true,
    "Order": 0,
    "Parameters": [],
    "ReturnTypes": [
      {
        "Type": "CoreProject.Utilities.DTOs.UserStatusResponseDto",
        "MediaTypes": [
          "text/plain",
          "application/json",
          "text/json"
        ],
        "StatusCode": 200
      },
      {
        "Type": "Microsoft.AspNetCore.Mvc.ProblemDetails",
        "MediaTypes": [
          "text/plain",
          "application/json",
          "text/json"
        ],
        "StatusCode": 401
      }
    ]
  },
  {
    "ContainingType": "MvcCoreProject.Controllers.Api.AttendanceApiController",
    "Method": "VerifyFace",
    "RelativePath": "api/attendance/verify-face",
    "HttpMethod": "POST",
    "IsController": true,
    "Order": 0,
    "Parameters": [
      {
        "Name": "request",
        "Type": "CoreProject.Utilities.DTOs.VerifyFaceRequestDto",
        "IsRequired": true
      }
    ],
    "ReturnTypes": [
      {
        "Type": "CoreProject.Utilities.DTOs.VerifyFaceResponseDto",
        "MediaTypes": [
          "text/plain",
          "application/json",
          "text/json"
        ],
        "StatusCode": 200
      },
      {
        "Type": "Microsoft.AspNetCore.Mvc.ProblemDetails",
        "MediaTypes": [
          "text/plain",
          "application/json",
          "text/json"
        ],
        "StatusCode": 400
      },
      {
        "Type": "Microsoft.AspNetCore.Mvc.ProblemDetails",
        "MediaTypes": [
          "text/plain",
          "application/json",
          "text/json"
        ],
        "StatusCode": 401
      }
    ]
  },
  {
    "ContainingType": "MvcCoreProject.Controllers.Api.AuthApiController",
    "Method": "ChangePassword",
    "RelativePath": "api/AuthApi/change-password",
    "HttpMethod": "POST",
    "IsController": true,
    "Order": 0,
    "Parameters": [
      {
        "Name": "request",
        "Type": "CoreProject.Utilities.DTOs.ChangePasswordRequestDto",
        "IsRequired": true
      }
    ],
    "ReturnTypes": [
      {
        "Type": "CoreProject.Utilities.DTOs.AuthResponseDto",
        "MediaTypes": [
          "text/plain",
          "application/json",
          "text/json"
        ],
        "StatusCode": 200
      },
      {
        "Type": "CoreProject.Utilities.DTOs.AuthResponseDto",
        "MediaTypes": [
          "text/plain",
          "application/json",
          "text/json"
        ],
        "StatusCode": 400
      },
      {
        "Type": "CoreProject.Utilities.DTOs.AuthResponseDto",
        "MediaTypes": [
          "text/plain",
          "application/json",
          "text/json"
        ],
        "StatusCode": 401
      }
    ]
  },
  {
    "ContainingType": "MvcCoreProject.Controllers.Api.AuthApiController",
    "Method": "Login",
    "RelativePath": "api/AuthApi/login",
    "HttpMethod": "POST",
    "IsController": true,
    "Order": 0,
    "Parameters": [
      {
        "Name": "request",
        "Type": "CoreProject.Utilities.DTOs.LoginRequestDto",
        "IsRequired": true
      }
    ],
    "ReturnTypes": [
      {
        "Type": "CoreProject.Utilities.DTOs.LoginResponseDto",
        "MediaTypes": [
          "text/plain",
          "application/json",
          "text/json"
        ],
        "StatusCode": 200
      },
      {
        "Type": "CoreProject.Utilities.DTOs.LoginResponseDto",
        "MediaTypes": [
          "text/plain",
          "application/json",
          "text/json"
        ],
        "StatusCode": 400
      },
      {
        "Type": "CoreProject.Utilities.DTOs.LoginResponseDto",
        "MediaTypes": [
          "text/plain",
          "application/json",
          "text/json"
        ],
        "StatusCode": 401
      }
    ]
  },
  {
    "ContainingType": "MvcCoreProject.Controllers.Api.AuthApiController",
    "Method": "Reset",
    "RelativePath": "api/AuthApi/reset",
    "HttpMethod": "POST",
    "IsController": true,
    "Order": 0,
    "Parameters": [
      {
        "Name": "request",
        "Type": "CoreProject.Utilities.DTOs.ResetRequestDto",
        "IsRequired": false
      }
    ],
    "ReturnTypes": [
      {
        "Type": "CoreProject.Utilities.DTOs.AuthResponseDto",
        "MediaTypes": [
          "text/plain",
          "application/json",
          "text/json"
        ],
        "StatusCode": 200
      },
      {
        "Type": "CoreProject.Utilities.DTOs.AuthResponseDto",
        "MediaTypes": [
          "text/plain",
          "application/json",
          "text/json"
        ],
        "StatusCode": 400
      },
      {
        "Type": "CoreProject.Utilities.DTOs.AuthResponseDto",
        "MediaTypes": [
          "text/plain",
          "application/json",
          "text/json"
        ],
        "StatusCode": 404
      }
    ]
  },
  {
    "ContainingType": "MvcCoreProject.Controllers.Api.DeviceApiController",
    "Method": "GetAccessControlState",
    "RelativePath": "api/device/access-control",
    "HttpMethod": "GET",
    "IsController": true,
    "Order": 0,
    "Parameters": [
      {
        "Name": "url",
        "Type": "System.String",
        "IsRequired": false
      }
    ],
    "ReturnTypes": [
      {
        "Type": "System.Int32",
        "MediaTypes": [
          "application/json"
        ],
        "StatusCode": 200
      }
    ]
  },
  {
    "ContainingType": "MvcCoreProject.Controllers.Api.DeviceApiController",
    "Method": "GetAccessControlStateByPath",
    "RelativePath": "api/device/access-control/{url}",
    "HttpMethod": "GET",
    "IsController": true,
    "Order": 0,
    "Parameters": [
      {
        "Name": "url",
        "Type": "System.String",
        "IsRequired": true
      }
    ],
    "ReturnTypes": []
  },
  {
    "ContainingType": "MvcCoreProject.Controllers.Api.DeviceApiController",
    "Method": "HealthCheck",
    "RelativePath": "api/device/health",
    "HttpMethod": "GET",
    "IsController": true,
    "Order": 0,
    "Parameters": [],
    "ReturnTypes": []
  },
  {
    "ContainingType": "MvcCoreProject.Controllers.Api.DeviceApiController",
    "Method": "GetDeviceStatus",
    "RelativePath": "api/device/status/{id}",
    "HttpMethod": "GET",
    "IsController": true,
    "Order": 0,
    "Parameters": [
      {
        "Name": "id",
        "Type": "System.Int32",
        "IsRequired": true
      }
    ],
    "ReturnTypes": []
  },
  {
    "ContainingType": "MvcCoreProject.Controllers.Api.DeviceApiController",
    "Method": "GetBatchDeviceStatus",
    "RelativePath": "api/device/status/batch",
    "HttpMethod": "POST",
    "IsController": true,
    "Order": 0,
    "Parameters": [
      {
        "Name": "ids",
        "Type": "System.Int32[]",
        "IsRequired": true
      }
    ],
    "ReturnTypes": []
  },
  {
    "ContainingType": "MvcCoreProject.Controllers.Api.FaceApiController",
    "Method": "Health",
    "RelativePath": "api/FaceApi/health",
    "HttpMethod": "GET",
    "IsController": true,
    "Order": 0,
    "Parameters": [],
    "ReturnTypes": []
  },
  {
    "ContainingType": "MvcCoreProject.Controllers.Api.FaceApiController",
    "Method": "Verify",
    "RelativePath": "api/FaceApi/verify",
    "HttpMethod": "POST",
    "IsController": true,
    "Order": 0,
    "Parameters": [
      {
        "Name": "file1",
        "Type": "Microsoft.AspNetCore.Http.IFormFile",
        "IsRequired": false
      },
      {
        "Name": "file2",
        "Type": "Microsoft.AspNetCore.Http.IFormFile",
        "IsRequired": false
      }
    ],
    "ReturnTypes": []
  }
]